setup.py
src/aiomongoengine/__init__.py
src/aiomongoengine/connection.py
src/aiomongoengine/database.py
src/aiomongoengine/document.py
src/aiomongoengine/errors.py
src/aiomongoengine/metaclasses.py
src/aiomongoengine/utils.py
src/aiomongoengine.egg-info/PKG-INFO
src/aiomongoengine.egg-info/SOURCES.txt
src/aiomongoengine.egg-info/dependency_links.txt
src/aiomongoengine.egg-info/requires.txt
src/aiomongoengine.egg-info/top_level.txt
src/aiomongoengine/fields/__init__.py
src/aiomongoengine/fields/base_field.py
src/aiomongoengine/fields/binary_field.py
src/aiomongoengine/fields/boolean_field.py
src/aiomongoengine/fields/datetime_field.py
src/aiomongoengine/fields/decimal_field.py
src/aiomongoengine/fields/dict_field.py
src/aiomongoengine/fields/dynamic_field.py
src/aiomongoengine/fields/embedded_document_field.py
src/aiomongoengine/fields/float_field.py
src/aiomongoengine/fields/int_field.py
src/aiomongoengine/fields/list_field.py
src/aiomongoengine/fields/objectid_field.py
src/aiomongoengine/fields/raw_field.py
src/aiomongoengine/fields/reference_field.py
src/aiomongoengine/fields/string_field.py
src/aiomongoengine/fields/uuid_field.py
src/aiomongoengine/query/__init__.py
src/aiomongoengine/query/base.py
src/aiomongoengine/query/query_operators.py
src/aiomongoengine/query/queryset.py
src/aiomongoengine/query/update_operators.py
src/aiomongoengine/query_builder/__init__.py
src/aiomongoengine/query_builder/field_list.py
src/aiomongoengine/query_builder/node.py
src/aiomongoengine/query_builder/transform.py