Metadata-Version: 2.1
Name: aiomongoengine
Version: 0.0.1.dev3
Summary: mongoengine wrapper for asyncio
Home-page: https://github.com/wangjiancn/aiomongoengine
Author: wangjiancn
Author-email: wangjianchn@outlook.com
Maintainer: smartpython
Maintainer-email: smartpython@outlook.com
License: MIT
Project-URL: Code, https://github.com/wangjiancn/aiomongoengine
Project-URL: Issue tracker, https://github.com/wangjiancn/aiomongoengine/issues
Keywords: mongoengine,asyncio,mongo
Platform: UNKNOWN
Classifier: Programming Language :: Python :: 3.6
Classifier: Programming Language :: Python :: 3.7
Classifier: Programming Language :: Python :: 3.8
Requires-Python: >=3.6
Provides-Extra: dev
